rastervision/aws_batch/__init__.py
rastervision/aws_batch/aws_batch_runner.py
rastervision/aws_batch/py.typed
rastervision_aws_batch-0.31.1.dist-info/METADATA
rastervision_aws_batch-0.31.1.dist-info/WHEEL
rastervision_aws_batch-0.31.1.dist-info/top_level.txt
rastervision_aws_batch-0.31.1.dist-info/RECORD
